LICENSE
README.md
setup.cfg
setup.py
bash_completion/ivre
bin/ivre
data/.empty
data/ike-vendor-ids
data/honeyd/sshd
doc/index.rst
doc/license-external.rst
doc/license.rst
doc/dev/index.rst
doc/dev/linting.rst
doc/dev/tests.rst
doc/dev/web-api.rst
doc/install/agents.rst
doc/install/config.rst
doc/install/docker.rst
doc/install/fast-install-and-first-run.rst
doc/install/index.rst
doc/install/installation.rst
doc/overview/faq.rst
doc/overview/index.rst
doc/overview/principles.rst
doc/overview/screenshots.rst
doc/screenshots/passive-cli.cast
doc/screenshots/passive-cli.svg
doc/screenshots/passive-view-cli.cast
doc/screenshots/passive-view-cli.svg
doc/screenshots/webui-details-heatmapzoom.png
doc/screenshots/webui-flow-details-flow.png
doc/screenshots/webui-flow-details-host.png
doc/screenshots/webui-flow-dns-halo.png
doc/screenshots/webui-flow-flow-map.png
doc/screenshots/webui-home-heatmap.png
doc/screenshots/webui-screenshots-solar-world.png
doc/screenshots/webui-tooltip-topenipvendors.png
doc/screenshots/webui-topproducts-80.png
doc/usage/active-recon.rst
doc/usage/flow.rst
doc/usage/index.rst
doc/usage/kibana.rst
doc/usage/passive.rst
doc/usage/use-cases.rst
doc/usage/web-ui.rst
docker/Vagrantfile
docker/agent/Dockerfile
docker/base/Dockerfile
docker/client/Dockerfile
docker/db/Dockerfile
docker/web/Dockerfile
docker/web/doku-conf-acl.auth.php
docker/web/doku-conf-local.php
docker/web/doku-conf-plugins.local.php
docker/web/doku-conf-users.auth.php
docker/web/nginx-default-site
docker/web-apache/Dockerfile
docker/web-apache/doku-conf-local.php
ivre/VERSION
ivre/__init__.py
ivre/activecli.py
ivre/agent.py
ivre/config.py
ivre/flow.py
ivre/geoiputils.py
ivre/graphroute.py
ivre/keys.py
ivre/mathutils.py
ivre/nmapopt.py
ivre/nmapout.py
ivre/passive.py
ivre/scanengine.py
ivre/target.py
ivre/utils.py
ivre/view.py
ivre/xmlnmap.py
ivre/zgrabout.py
ivre.egg-info/PKG-INFO
ivre.egg-info/SOURCES.txt
ivre.egg-info/dependency_links.txt
ivre.egg-info/requires.txt
ivre.egg-info/top_level.txt
ivre/active/__init__.py
ivre/active/cpe.py
ivre/active/data.py
ivre/analyzer/__init__.py
ivre/analyzer/dicom.py
