Metadata-Version: 2.1
Name: ivre
Version: 0.9.19
Summary: Network recon framework
Home-page: https://ivre.rocks/
Author: Pierre LALET
Author-email: pierre@droids-corp.org
License: GPLv3+
Download-URL: https://github.com/ivre/ivre/tarball/master
Keywords: network,network recon,network cartography,nmap,masscan,zmap,zgrab,zdns,bro,zeek
Platform: UNKNOWN
Classifier: Development Status :: 5 - Production/Stable
Classifier: Environment :: Console
Classifier: Environment :: Web Environment
Classifier: Intended Audience :: Developers
Classifier: Intended Audience :: Information Technology
Classifier: Intended Audience :: Science/Research
Classifier: Intended Audience :: System Administrators
Classifier: Intended Audience :: Telecommunications Industry
Classifier: License :: OSI Approved :: GNU General Public License v3 or later (GPLv3+)
Classifier: Programming Language :: Python :: 3
Classifier: Programming Language :: Python :: 3.7
Classifier: Programming Language :: Python :: 3.8
Classifier: Programming Language :: Python :: 3.9
Classifier: Programming Language :: Python :: 3.10
Classifier: Programming Language :: Python :: 3.11
Classifier: Topic :: Scientific/Engineering :: Information Analysis
Classifier: Topic :: Security
Classifier: Topic :: System :: Networking
Classifier: Topic :: System :: Networking :: Monitoring
Classifier: Topic :: System :: Software Distribution
Requires-Python: >=3.7, <4
Provides-Extra: MongoDB mongo+srv URIs
Provides-Extra: TinyDB (experimental)
Provides-Extra: PostgreSQL (experimental)
Provides-Extra: Elasticsearch (experimental)
Provides-Extra: GSSAPI authentication for MongoDB
Provides-Extra: GSSAPI authentication for HTTP
Provides-Extra: Screenshots
Provides-Extra: MediaWiki integration
Provides-Extra: 3D traceroute graphs
Provides-Extra: Plots
Provides-Extra: JA3 fingerprints from reverse-ssl services
License-File: LICENSE
